aptivate_cli/__init__.py
aptivate_cli/cli.py
aptivate_cli/cmd.py
aptivate_cli/config.py
aptivate_cli/settings.py
aptivate_cli/cligroups/__init__.py
aptivate_cli/cligroups/ci/__init__.py
aptivate_cli/cligroups/ci/commands.py
aptivate_cli/cligroups/deploy/__init__.py
aptivate_cli/cligroups/deploy/commands.py
aptivate_cli/cligroups/deployment/__init__.py
aptivate_cli/cligroups/deployment/commands.py
aptivate_cli/cligroups/metrics/__init__.py
aptivate_cli/cligroups/metrics/commands.py
aptivate_cli/cligroups/metrics/outreach.py
aptivate_cli/cligroups/metrics/pykanbantool/__init__.py
aptivate_cli/cligroups/metrics/pykanbantool/api.py
aptivate_cli/cligroups/molecule/__init__.py
aptivate_cli/cligroups/molecule/commands.py
aptivate_cli/cligroups/remotes/__init__.py
aptivate_cli/cligroups/remotes/commands.py
aptivate_cli/cligroups/templates/__init__.py
aptivate_cli/cligroups/templates/commands.py
aptivate_cli/cligroups/unchecked/__init__.py
aptivate_cli/cligroups/unchecked/commands.py
aptivate_cli-0.0.17.dist-info/LICENSE
aptivate_cli-0.0.17.dist-info/METADATA
aptivate_cli-0.0.17.dist-info/WHEEL
aptivate_cli-0.0.17.dist-info/entry_points.txt
aptivate_cli-0.0.17.dist-info/top_level.txt
aptivate_cli-0.0.17.dist-info/RECORD
