Metadata-Version: 2.1
Name: aptivate-cli
Version: 0.0.17
Summary: Fully automated luxury Aptivate command line interface.
Home-page: https://git.coop/aptivate/internal-tools/aptivate-cli
Author: Aptivate Hackers
Author-email: carers+aptivate-cli@aptivate.org
License: GPLv3
Platform: any
Classifier: Programming Language :: Python :: 3
Classifier: Environment :: Console
Classifier: Intended Audience :: Developers
Requires-Dist: click
Requires-Dist: click-datetime
Requires-Dist: colorama
Requires-Dist: cookiecutter
